cuteuid/__init__.py
cuteuid/playground.py
cuteuid/preprocess.py
cuteuid/core/__init__.py
cuteuid/core/converters.py
cuteuid/core/kinds/__init__.py
cuteuid/core/kinds/base_uid.py
cuteuid/core/kinds/emoji_uid.py
cuteuid/core/kinds/leet_uid.py
cuteuid/data/emojis.json
cuteuid/data/words.json
src/cuteuid/__init__.py
cuteuid_alexredmon-0.0.10.dist-info/LICENSE
cuteuid_alexredmon-0.0.10.dist-info/METADATA
cuteuid_alexredmon-0.0.10.dist-info/WHEEL
cuteuid_alexredmon-0.0.10.dist-info/top_level.txt
cuteuid_alexredmon-0.0.10.dist-info/RECORD
